my_llms_runtime/__init__.py
my_llms_runtime/pyarmor_runtime.so
superai_llms/__init__.py
superai_llms/settings.py
superai_llms/api/__init__.py
superai_llms/api/services/__init__.py
superai_llms/api/services/llm.py
superai_llms/api/v1/__init__.py
superai_llms/api/v1/schemas.py
superai_llms/cache/__init__.py
superai_llms/cache/redis.py
superai_llms/chat_models/__init__.py
superai_llms/chat_models/host_llm.py
superai_llms/chat_models/minimax.py
superai_llms/chat_models/proxy_llm.py
superai_llms/chat_models/qwen.py
superai_llms/chat_models/sensetime.py
superai_llms/chat_models/superai_chatmodel.py
superai_llms/chat_models/superai_openai.py
superai_llms/chat_models/wenxin.py
superai_llms/chat_models/zhipuai.py
superai_llms/chat_models/interface/__init__.py
superai_llms/chat_models/interface/minimax.py
superai_llms/chat_models/interface/openai.py
superai_llms/chat_models/interface/types.py
superai_llms/chat_models/interface/utils.py
superai_llms/chat_models/interface/wenxin.py
superai_llms/chat_models/interface/zhipuai.py
superai_llms/database/__init__.py
superai_llms/database/base.py
superai_llms/database/service.py
superai_llms/database/models/__init__.py
superai_llms/database/models/base.py
superai_llms/database/models/config.py
superai_llms/database/models/llm_server.py
superai_llms/database/models/stream_msg.py
superai_llms/database/models/user.py
superai_llms/errorcode/__init__.py
superai_llms/errorcode/user.py
superai_llms/interface/__init__.py
superai_llms/interface/custom_lists.py
superai_llms/interface/utils.py
superai_llms/interface/embeddings/__init__.py
superai_llms/interface/embeddings/base.py
superai_llms/interface/embeddings/custom.py
superai_llms/interface/embeddings/host_embedding.py
superai_llms/interface/embeddings/huggingfacegte.py
superai_llms/interface/embeddings/huggingfacemultilingual.py
superai_llms/interface/embeddings/wenxin.py
superai_llms/interface/importing/__init__.py
superai_llms/interface/importing/utils.py
superai_llms-1.2.1.15.dist-info/METADATA
superai_llms-1.2.1.15.dist-info/WHEEL
superai_llms-1.2.1.15.dist-info/top_level.txt
superai_llms-1.2.1.15.dist-info/RECORD
