Metadata-Version: 2.4
Name: superai_llms
Version: 1.2.1.15
Summary: superai llms modules
Home-page: https://github.com/xxx/superai
Author: Owen
Author-email: contact@Owen.com
License: Apache 2.0
Classifier: Programming Language :: Python :: 3
Classifier: Programming Language :: Python :: 3.6
Classifier: Programming Language :: Python :: 3.7
Classifier: Programming Language :: Python :: 3.8
Classifier: Programming Language :: Python :: 3.9
Classifier: License :: OSI Approved :: Apache Software License
Classifier: Operating System :: OS Independent
Requires-Python: >=3.6
Requires-Dist: requests>=2.32.4
Requires-Dist: pyarmor>=9.1.7
Requires-Dist: twine>=6.1.0
Requires-Dist: langchain>=0.3.25
Requires-Dist: langchain-community>=0.3.24
Requires-Dist: Pillow>=10.4.0
Requires-Dist: pydantic
Requires-Dist: tiktoken
Requires-Dist: loguru>=0.7.1
Requires-Dist: openai>=1.70.0
Requires-Dist: langchain_openai>=0.3.12
Requires-Dist: langchain-ollama>=0.3.0
Requires-Dist: langchain-google-genai>=2.1.0
Requires-Dist: langchain-anthropic>=0.3.10
Requires-Dist: langchain-deepseek>=0.1.3
Requires-Dist: langgraph>=0.3.27
Requires-Dist: redis>=5.0.0
Requires-Dist: sqlmodel>=0.0.16
Requires-Dist: pymysql>=0.10.1
Requires-Dist: cryptography>=44.0.1
Requires-Dist: zhipuai
Requires-Dist: fastmcp>=2.6.1
Dynamic: author
Dynamic: author-email
Dynamic: classifier
Dynamic: description-content-type
Dynamic: home-page
Dynamic: license
Dynamic: requires-dist
Dynamic: requires-python
Dynamic: summary
